dlt_cratedb/__init__.py
dlt_cratedb/py.typed
dlt_cratedb/impl/__init__.py
dlt_cratedb/impl/cratedb/__init__.py
dlt_cratedb/impl/cratedb/configuration.py
dlt_cratedb/impl/cratedb/cratedb.py
dlt_cratedb/impl/cratedb/factory.py
dlt_cratedb/impl/cratedb/sql_client.py
dlt_cratedb/impl/cratedb/utils.py
dlt_cratedb/patch/__init__.py
dlt_cratedb/patch/utils.py
dlt_cratedb-0.0.2.dist-info/licenses/LICENSE.txt
dlt_cratedb-0.0.2.dist-info/METADATA
dlt_cratedb-0.0.2.dist-info/WHEEL
dlt_cratedb-0.0.2.dist-info/top_level.txt
dlt_cratedb-0.0.2.dist-info/RECORD
