Metadata-Version: 2.4
Name: dlt-cratedb
Version: 0.0.2
Summary: dlt destination adapter for CrateDB
Author-email: Andreas Motl <andreas.motl@crate.io>
License-Expression: Apache-2.0
Project-URL: Changelog, https://github.com/crate/dlt-cratedb/blob/main/CHANGES.md
Project-URL: Documentation, https://github.com/crate/dlt-cratedb/tree/main/docs
Project-URL: Issues, https://github.com/crate/dlt-cratedb/issues
Project-URL: Repository, https://github.com/crate/dlt-cratedb
Keywords: CrateDB,data,destination,dlt,elt,etl,i/o,postgresql,sql
Classifier: Development Status :: 3 - Alpha
Classifier: Environment :: Plugins
Classifier: Intended Audience :: Developers
Classifier: Intended Audience :: Education
Classifier: Intended Audience :: Information Technology
Classifier: Intended Audience :: Manufacturing
Classifier: Intended Audience :: Science/Research
Classifier: Intended Audience :: System Administrators
Classifier: Intended Audience :: Telecommunications Industry
Classifier: Operating System :: OS Independent
Classifier: Operating System :: POSIX :: Linux
Classifier: Operating System :: Unix
Classifier: Programming Language :: Python
Classifier: Programming Language :: Python :: 3 :: Only
Classifier: Programming Language :: Python :: 3.9
Classifier: Programming Language :: Python :: 3.10
Classifier: Programming Language :: Python :: 3.11
Classifier: Programming Language :: Python :: 3.12
Classifier: Programming Language :: Python :: 3.13
Classifier: Programming Language :: Python :: Implementation :: CPython
Classifier: Programming Language :: Python :: Implementation :: PyPy
Classifier: Programming Language :: SQL
Classifier: Topic :: Adaptive Technologies
Classifier: Topic :: Communications
Classifier: Topic :: Database
Classifier: Topic :: Documentation
Classifier: Topic :: Education
Classifier: Topic :: Internet
Classifier: Topic :: Office/Business
Classifier: Topic :: Scientific/Engineering
Classifier: Topic :: Scientific/Engineering :: Information Analysis
Classifier: Topic :: Scientific/Engineering :: Interface Engine/Protocol Translator
Classifier: Topic :: Software Development :: Libraries
Classifier: Topic :: Software Development :: Pre-processors
Classifier: Topic :: Software Development :: Testing
Classifier: Topic :: Software Development :: Version Control
Classifier: Topic :: System :: Archiving
Classifier: Topic :: System :: Benchmark
Classifier: Topic :: System :: Clustering
Classifier: Topic :: System :: Distributed Computing
Classifier: Topic :: System :: Logging
Classifier: Topic :: System :: Monitoring
Classifier: Topic :: System :: Networking
Classifier: Topic :: System :: Systems Administration
Classifier: Topic :: Text Processing
Classifier: Topic :: Utilities
Requires-Python: >=3.9
License-File: LICENSE.txt
Requires-Dist: dlt[postgres]
Provides-Extra: develop
Requires-Dist: mypy<1.13,>=1.11; extra == "develop"
Requires-Dist: poethepoet<1; extra == "develop"
Requires-Dist: pyproject-fmt<3; extra == "develop"
Requires-Dist: ruff<0.6; extra == "develop"
Requires-Dist: validate-pyproject<1,>=0.23; extra == "develop"
Provides-Extra: release
Requires-Dist: build<2; extra == "release"
Requires-Dist: twine<7,>=6; extra == "release"
Provides-Extra: test
Requires-Dist: duckdb; extra == "test"
Requires-Dist: pytest<9; extra == "test"
Requires-Dist: pytest-cov<6; extra == "test"
Requires-Dist: sqlfluff<2.4; extra == "test"
Dynamic: license-file
